docs/source/conf.py
skfb/__init__.py
skfb/core/__init__.py
skfb/core/array.py
skfb/estimators/__init__.py
skfb/estimators/_anomaly.py
skfb/estimators/_multi_threshold.py
skfb/estimators/_threshold.py
skfb/estimators/base.py
skfb/experimental/__init__.py
skfb/experimental/enable_error_rejection_loss.py
skfb/experimental/enable_multi_threshold_fallback_classifier_cv.py
skfb/metrics/__init__.py
skfb/metrics/_classification.py
skfb/metrics/_common.py
skfb/metrics/_plot.py
skfb/metrics/_ranking.py
skfb/utils/_legacy.py
scikit_fallback-0.1.1.post0.dist-info/LICENSE
scikit_fallback-0.1.1.post0.dist-info/METADATA
scikit_fallback-0.1.1.post0.dist-info/WHEEL
scikit_fallback-0.1.1.post0.dist-info/top_level.txt
scikit_fallback-0.1.1.post0.dist-info/RECORD
