Metadata-Version: 2.1
Name: scikit-fallback
Version: 0.1.1.post0
Summary: Machine learning with a reject option
Author: Sanjar Ad[yi]lov
Maintainer: Sanjar Ad[yi]lov
License: BSD 3-Clause License
Project-URL: Homepage, https://github.com/sanjaradylov/scikit-fallback
Classifier: Development Status :: 5 - Production/Stable
Classifier: Intended Audience :: Science/Research
Classifier: Intended Audience :: Developers
Classifier: License :: OSI Approved :: BSD License
Classifier: Operating System :: Microsoft :: Windows
Classifier: Operating System :: POSIX
Classifier: Operating System :: Unix
Classifier: Operating System :: MacOS
Classifier: Programming Language :: Python
Classifier: Programming Language :: Python :: 3
Classifier: Programming Language :: Python :: 3.9
Classifier: Programming Language :: Python :: 3.10
Classifier: Programming Language :: Python :: 3.11
Classifier: Programming Language :: Python :: 3.12
Classifier: Programming Language :: Python :: Implementation :: CPython
Classifier: Topic :: Software Development
Classifier: Topic :: Scientific/Engineering
Classifier: Topic :: Scientific/Engineering :: Artificial Intelligence
Requires-Python: >=3.9
License-File: LICENSE
Requires-Dist: scikit-learn>=1.0
Provides-Extra: dev
Requires-Dist: jupyterlab; extra == "dev"
Provides-Extra: examples
Requires-Dist: matplotlib>=3.0; extra == "examples"
Provides-Extra: tests
Requires-Dist: black>=24.4.0; extra == "tests"
Requires-Dist: matplotlib>=3.0; extra == "tests"
Requires-Dist: pre-commit>=3.7.0; extra == "tests"
Requires-Dist: pylint~=3.1.0; extra == "tests"
Requires-Dist: pytest>=8.0; extra == "tests"
